process_image/__init__.py
process_image/processing/__init__.py
process_image/processing/combination.py
process_image/processing/transformation.py
process_image/utils/__init__.py
process_image/utils/io.py
process_image/utils/plot.py
process_image-0.0.3.dist-info/METADATA
process_image-0.0.3.dist-info/WHEEL
process_image-0.0.3.dist-info/top_level.txt
process_image-0.0.3.dist-info/RECORD
