Metadata-Version: 2.1
Name: process-image
Version: 0.0.3
Summary: Image Processing Package using skimage
Home-page: https://github.com/thiagodruvis/Descomplicando_a_criacao_de_pacotes_de_processamento_de_imagens_em_Python
Author: Thiago
License: UNKNOWN
Platform: UNKNOWN
Requires-Python: >=3.8
Requires-Dist: matplotlib
Requires-Dist: numpy
Requires-Dist: scikit-image (>=0.16.1)
